README.rst
setup.py
x/__init__.py
x/apis.py
x/gallery.py
x_py.egg-info/PKG-INFO
x_py.egg-info/SOURCES.txt
x_py.egg-info/dependency_links.txt
x_py.egg-info/top_level.txt