Metadata-Version: 1.0
Name: x-py
Version: 0.0.1
Summary: x-py
Home-page: https://github.com/yoshow/x-py
Author: yoshow
Author-email: ruanyu@live.com
License: MIT License
Platform: all
